array_format_optimizer.py
borsa_client.py
borsa_mcp_server.py
borsa_models.py
compact_json_optimizer.py
fon_mevzuat_kisa.py
token_optimizer.py
iflow_mcp_saidsurucu_borsa_mcp-0.7.0.dist-info/licenses/LICENSE
models/__init__.py
models/base.py
models/btcturk_models.py
models/buffett_models.py
models/calendar_models.py
models/coinbase_models.py
models/comprehensive_analysis_models.py
models/dovizcom_models.py
models/financial_ratios_models.py
models/kap_models.py
models/mynet_models.py
models/regulation_models.py
models/tcmb_models.py
models/tefas_models.py
models/yfinance_models.py
providers/__init__.py
providers/btcturk_provider.py
providers/buffett_analyzer_provider.py
providers/coinbase_provider.py
providers/dovizcom_auth.py
providers/dovizcom_calendar_provider.py
providers/dovizcom_provider.py
providers/dovizcom_tahvil_provider.py
providers/financial_ratios_provider.py
providers/isyatirim_provider.py
providers/kap_provider.py
providers/mynet_provider.py
providers/tcmb_provider.py
providers/tefas_provider.py
providers/worldbank_provider.py
providers/yfinance_provider.py
iflow_mcp_saidsurucu_borsa_mcp-0.7.0.dist-info/METADATA
iflow_mcp_saidsurucu_borsa_mcp-0.7.0.dist-info/WHEEL
iflow_mcp_saidsurucu_borsa_mcp-0.7.0.dist-info/entry_points.txt
iflow_mcp_saidsurucu_borsa_mcp-0.7.0.dist-info/top_level.txt
iflow_mcp_saidsurucu_borsa_mcp-0.7.0.dist-info/RECORD
