Metadata-Version: 2.4
Name: iflow-mcp_saidsurucu_borsa-mcp
Version: 0.7.0
Summary: A modular MCP Server for Borsa Istanbul (BIST) data using KAP and Yahoo Finance.
Requires-Python: >=3.11
License-File: LICENSE
Requires-Dist: fastmcp>=2.14.0
Requires-Dist: pydantic>=2.7.0
Requires-Dist: httpx>=0.27.0
Requires-Dist: pdfplumber>=0.11.0
Requires-Dist: beautifulsoup4>=4.12.3
Requires-Dist: lxml>=5.2.0
Requires-Dist: yfinance>=0.2.37
Requires-Dist: pandas>=2.0.0
Requires-Dist: markitdown>=0.1.1
Requires-Dist: openpyxl>=3.1.5
Requires-Dist: requests>=2.31.0
Dynamic: license-file
